orjsonless_pickledb.py
orjsonless_pickledb-1.3.2.post4.dist-info/WHEEL
orjsonless_pickledb-1.3.2.post4.dist-info/METADATA
orjsonless_pickledb-1.3.2.post4.dist-info/RECORD
