Metadata-Version: 2.4
Name: orjsonless_pickledb
Version: 1.3.2.post4
Summary: orjson-less fork of pickledb
Keywords: pickledb,pickle db,database
Author-email: César Berriot <berriot.cesar@gmail.com>
License-Expression: BSD-3-Clause
Requires-Dist: aiofiles
Project-URL: Homepage, https://github.com/CesarBerriot
